stenops/__init__.py
stenops/acrostic/__init__.py
stenops/acrostic/app.py
stenops/acrostic/chains.py
stenops/acrostic/params.py
stenops/acrostic/prompts.py
stenops/acrostic/transforms.py
stenops-0.1.0.dist-info/METADATA
stenops-0.1.0.dist-info/WHEEL
stenops-0.1.0.dist-info/RECORD
