Metadata-Version: 2.1
Name: stenops
Version: 0.1.0
Summary: 
Author: Naka
Author-email: alex.naka@gmail.com
Requires-Python: >=3.10,<4.0
Classifier: Programming Language :: Python :: 3
Classifier: Programming Language :: Python :: 3.10
Classifier: Programming Language :: Python :: 3.11
Requires-Dist: gradio (>=3.20.1,<4.0.0)
Requires-Dist: langchain (>=0.0.107,<0.0.108)
Requires-Dist: nltk (>=3.8.1,<4.0.0)
Requires-Dist: openai (>=0.27.2,<0.28.0)
Requires-Dist: pandas (>=1.5.3,<2.0.0)
Requires-Dist: pydantic (>=1.10.6,<2.0.0)
Requires-Dist: python-dotenv (>=1.0.0,<2.0.0)
Requires-Dist: scikit-learn (>=1.2.2,<2.0.0)
Requires-Dist: seaborn (>=0.12.2,<0.13.0)
Requires-Dist: tqdm (>=4.65.0,<5.0.0)
Requires-Dist: umap-learn (>=0.5.3,<0.6.0)
